{
  "author": "@smashingmag",
  "commentCount": 219,
  "description": "Take a look at 80+ gorgeous typefaces for professional design, based upon suggestions from designers and web developers all over the world.",
  "image": "https://media-mediatemple.netdna-ssl.com/wp-content/uploads/images/post-pictures/80-beautiful.png",
  "objectID": "https://www.smashingmagazine.com/2007/08/80-beautiful-fonts-typefaces-for-professional-design/",
  "publishedDate": 1186531288,
  "tags": [
    "Downloads",
    "Fonts",
    "Freebies",
    "Typography"
  ],
  "title": "80 Beautiful Typefaces For Professional Design",
  "url": "https://www.smashingmagazine.com/2007/08/80-beautiful-fonts-typefaces-for-professional-design/"
}