{
  "author": "@smashingmag",
  "commentCount": 37,
  "description": "MooTools is a JavaScript framework that focus on being flexible, modular and compact. While still not on par in number of resources with other JavaScript frameworks such as jQuery, the MooTools com...",
  "image": "https://media-mediatemple.netdna-ssl.com/wp-content/uploads/images/post-pictures/mootools.jpg",
  "objectID": "https://www.smashingmagazine.com/2009/07/mootools-tutorials-and-resources-round-up/",
  "publishedDate": 1248750991,
  "tags": [
    "Resources"
  ],
  "title": "MooTools Tutorials and Resources Round-Up",
  "url": "https://www.smashingmagazine.com/2009/07/mootools-tutorials-and-resources-round-up/"
}