{
  "author": "Daved Brosche",
  "authorUrl": "https://www.smashingmagazine.com/author/daved-brosche/",
  "commentCount": 75,
  "description": "Shadows can add a lot to a photograph. They can emphasize emotions, create surreal images, and be used in a variety of ways. While strong use of shadows in color photographs tends to be mostly used...",
  "image": "https://media-mediatemple.netdna-ssl.com/wp-content/uploads/images/post-pictures/shadows.jpg",
  "objectID": "https://www.smashingmagazine.com/2009/03/showcase-of-beautiful-shadow-photography/",
  "publishedDate": 1235918205,
  "tags": [
    {
      "name": "Photography",
      "slug": "photography"
    }
  ],
  "title": "Showcase Of Beautiful Shadow Photography",
  "url": "https://www.smashingmagazine.com/2009/03/showcase-of-beautiful-shadow-photography/"
}