{
  "author": "Sharon Ross",
  "authorUrl": "https://www.smashingmagazine.com/author/sharon-ross/",
  "commentCount": 52,
  "description": "Everyday we see objects consisting of one, two, and three dimensions. By incorporating mathematics with design, the outcome of computer generated fractals is based upon complexity, creativity and p...",
  "image": "https://media-mediatemple.netdna-ssl.com/wp-content/uploads/images/post-pictures/fractalsbw.jpg",
  "objectID": "https://www.smashingmagazine.com/2009/04/black-and-white-fractals-that-capture-creativity/",
  "publishedDate": 1240779684,
  "tags": [
    {
      "name": "Mathematics",
      "slug": "mathematics"
    }
  ],
  "title": "Black and White Fractals That Capture Creativity",
  "url": "https://www.smashingmagazine.com/2009/04/black-and-white-fractals-that-capture-creativity/"
}