{
  "author": "Kat Neville",
  "authorUrl": "https://www.smashingmagazine.com/author/kat-neville/",
  "commentCount": 197,
  "description": "Here are some general guidelines, best practices and examples that will help you make sure your invoices are up to spec.",
  "image": "https://media-mediatemple.netdna-ssl.com/wp-content/uploads/images/post-pictures/juddling-lego-illu.jpg",
  "objectID": "https://www.smashingmagazine.com/2009/11/invoice-like-a-pro/",
  "publishedDate": 1257420329,
  "tags": [
    {
      "name": "Business",
      "slug": "business"
    },
    {
      "name": "Clients",
      "slug": "clients"
    },
    {
      "name": "Contracts",
      "slug": "contracts"
    },
    {
      "name": "Inspiration",
      "slug": "inspiration"
    },
    {
      "name": "Invoicing",
      "slug": "invoicing"
    },
    {
      "name": "Useful",
      "slug": "useful"
    }
  ],
  "title": "Invoice Like A Pro: Examples and Best Practices",
  "url": "https://www.smashingmagazine.com/2009/11/invoice-like-a-pro/"
}