{
  "author": "@smashingmag",
  "commentCount": 155,
  "description": "In this post we release 2 free high-quality WordPress magazine-themes. The themes include full PSD-templates and can be used without any restrictions whatsoever. The themes were commissioned by Sma...",
  "image": "https://media-mediatemple.netdna-ssl.com/wp-content/uploads/images/post-pictures/delli3.jpg",
  "objectID": "https://www.smashingmagazine.com/2009/01/vintage-and-blues-wordpress-themes/",
  "publishedDate": 1233130815,
  "tags": [
    "Downloads",
    "Freebies",
    "Themes",
    "Vintage"
  ],
  "title": "Vintage and Blues WordPress Themes",
  "url": "https://www.smashingmagazine.com/2009/01/vintage-and-blues-wordpress-themes/"
}