{
  "author": "@smashingmag",
  "commentCount": 132,
  "description": "No, we&#39;re not giving anything away in this post. Instead, we&#39;ve got some work to do, and we need you to play an important role in it. Our most interesting (and important) project for 2009 is someth...",
  "image": "https://media-mediatemple.netdna-ssl.com/wp-content/uploads/images/post-pictures/pencilsiconset.jpg",
  "objectID": "https://www.smashingmagazine.com/2009/02/the-smashing-book-join-in/",
  "publishedDate": 1235476941,
  "tags": [
    "Smashing Books"
  ],
  "title": "The Smashing Book: Join In!",
  "url": "https://www.smashingmagazine.com/2009/02/the-smashing-book-join-in/"
}