{
  "author": "The Smashing Editorial",
  "authorUrl": "https://www.smashingmagazine.com/author/admin/",
  "commentCount": 68,
  "description": "Christmas is coming and, of course, it&#39;s just the right time to provide you with some nice freebies to fresh up your designs. To celebrate the holidays, our friends from IconEden designed &quot;Smashing...",
  "image": "https://media-mediatemple.netdna-ssl.com/wp-content/uploads/images/post-pictures/christmas.jpg",
  "objectID": "https://www.smashingmagazine.com/2009/12/free-smashing-christmas-icon-set/",
  "publishedDate": 1260269846,
  "tags": [
    {
      "name": "Christmas",
      "slug": "christmas"
    },
    {
      "name": "Downloads",
      "slug": "downloads"
    },
    {
      "name": "Freebies",
      "slug": "freebies"
    },
    {
      "name": "Icons",
      "slug": "icons"
    }
  ],
  "title": "Free Smashing Christmas Icon Set",
  "url": "https://www.smashingmagazine.com/2009/12/free-smashing-christmas-icon-set/"
}