{
  "author": "Jad Limcaco",
  "authorUrl": "https://www.smashingmagazine.com/author/jad-limcaco/",
  "commentCount": 6,
  "description": "Inspiration comes from a lot of places. Today, I would like to showcase 18 of the most interesting Ronald McDonald illustrations that I could find for your inspiration.",
  "image": "https://media-mediatemple.netdna-ssl.com/wp-content/uploads/images/post-pictures/illus-mcdonald.png",
  "objectID": "https://www.smashingmagazine.com/2009/11/18-interesting-ronald-mcdonald-illustrations/",
  "publishedDate": 1257336765,
  "tags": [
    {
      "name": "Design Informer",
      "slug": "design-informer"
    }
  ],
  "title": "18 Interesting Ronald McDonald Illustrations",
  "url": "https://www.smashingmagazine.com/2009/11/18-interesting-ronald-mcdonald-illustrations/"
}