{
  "author": "Dan Redding",
  "authorUrl": "https://www.smashingmagazine.com/author/dan-redding/",
  "commentCount": 85,
  "description": "The Internet is a medium that is evolving at breakneck speed. It&#39;s a wild organism of sweeping cultural change — one that leaves the carcasses of dead media forms in its sizeable wake. It&#39;s transfo...",
  "image": "https://media-mediatemple.netdna-ssl.com/wp-content/uploads/2013/07/dontfearinternet_mini.png",
  "objectID": "https://www.smashingmagazine.com/2010/08/the-future-of-the-internet/",
  "publishedDate": 1281489931,
  "tags": [
    {
      "name": "Future",
      "slug": "future"
    },
    {
      "name": "Web Design",
      "slug": "web-design"
    }
  ],
  "title": "The Future Of The Internet",
  "url": "https://www.smashingmagazine.com/2010/08/the-future-of-the-internet/"
}