{
  "author": "Oleg Mokhov",
  "authorUrl": "https://www.smashingmagazine.com/author/oleg-mokhov/",
  "commentCount": 114,
  "description": "Almost all of us listen to music. We listen at home, while working, on the subway, while driving, while running. Yet many of us don&#39;t think of music as much more than entertainment. Did you know th...",
  "image": "https://media-mediatemple.netdna-ssl.com/wp-content/uploads/images/post-pictures/music.png",
  "objectID": "https://www.smashingmagazine.com/2010/07/add-music-to-your-workflow-to-improve-results/",
  "publishedDate": 1278196569,
  "tags": [
    {
      "name": "Music",
      "slug": "music"
    },
    {
      "name": "Opinion Column",
      "slug": "opinion-column"
    },
    {
      "name": "Workflow",
      "slug": "workflow"
    }
  ],
  "title": "Add Music To Your Workflow To Improve Results",
  "url": "https://www.smashingmagazine.com/2010/07/add-music-to-your-workflow-to-improve-results/"
}