{
  "author": "@designinformer",
  "commentCount": 83,
  "description": "Design is everywhere. We see it in on billboards as we drive down the street. When we go to a restaurant and look at the menus, we see it.",
  "image": "https://media-mediatemple.netdna-ssl.com/wp-content/uploads/images/post-pictures/black-art-anthony-hare.jpg",
  "objectID": "https://www.smashingmagazine.com/2010/02/how-to-drastically-improve-your-designs/",
  "publishedDate": 1265585752,
  "tags": [
    "Design Informer",
    "Techniques",
    "Workflow"
  ],
  "title": "How to Drastically Improve Your Designs",
  "url": "https://www.smashingmagazine.com/2010/02/how-to-drastically-improve-your-designs/"
}