{
  "author": "@danny_cooper",
  "commentCount": 49,
  "description": "Concise 15-step guide to creating awesome WordPress-powered websites",
  "image": "https://media-mediatemple.netdna-ssl.com/wp-content/uploads/images/post-pictures/wordpress-files-illu101.jpg",
  "objectID": "https://www.smashingmagazine.com/2011/12/15-step-checklist-creating-perfect-wordpress-website/",
  "publishedDate": 1323845527,
  "tags": [
    "Techniques (WP)",
    "Themes",
    "Tutorials"
  ],
  "title": "15-Step Checklist To Creating The Perfect WordPress Website",
  "url": "https://www.smashingmagazine.com/2011/12/15-step-checklist-creating-perfect-wordpress-website/"
}