{
  "author": "Lyndon Cerejo",
  "authorUrl": "https://www.smashingmagazine.com/author/lyndon-cerejo/",
  "commentCount": 39,
  "description": "For the past few years, we&#39;ve heard pundits declaring each year as &quot;year of the mobile Web&quot;; each year trying to sound more convincing than the previous. Whether 2011 will be the real &quot;year of the ...",
  "image": "https://media-mediatemple.netdna-ssl.com/wp-content/uploads/2011/04/user-centered-mobile-design-lifecycle.jpg",
  "objectID": "https://www.smashingmagazine.com/2011/05/a-user-centered-approach-to-web-design-for-mobile-devices/",
  "publishedDate": 1304306988,
  "tags": [
    {
      "name": "Strategy",
      "slug": "strategy"
    }
  ],
  "title": "A User-Centered Approach To Web Design For Mobile Devices",
  "url": "https://www.smashingmagazine.com/2011/05/a-user-centered-approach-to-web-design-for-mobile-devices/"
}