{
  "author": "Louis Lazaris",
  "authorUrl": "https://www.smashingmagazine.com/author/louis-lazaris/",
  "commentCount": 153,
  "description": "Many people fear the Object Oriented CSS ideology because it seems to go against many of the so-called “best practices” we’ve learned. But once the long-term benefits of using OOCSS are understood,...",
  "image": "https://media-mediatemple.netdna-ssl.com/wp-content/uploads/2012/11/ipad27-500.jpg",
  "objectID": "https://www.smashingmagazine.com/2011/12/an-introduction-to-object-oriented-css-oocss/",
  "publishedDate": 1323669787,
  "tags": [
    {
      "name": "CSS",
      "slug": "css"
    }
  ],
  "title": "An Introduction To Object Oriented CSS (OOCSS)",
  "url": "https://www.smashingmagazine.com/2011/12/an-introduction-to-object-oriented-css-oocss/"
}