{
  "author": "Scotty Vernon",
  "authorUrl": "https://www.smashingmagazine.com/author/scotty-vernon/",
  "commentCount": 64,
  "description": "Designers are constantly striving to create eye-catching designs without losing the usability features that add significant importance to the experience of online shopping. Today&#39;s showcase present...",
  "image": "https://media-mediatemple.netdna-ssl.com/wp-content/uploads/images/post-pictures/e-commerce-sites.jpg",
  "objectID": "https://www.smashingmagazine.com/2011/01/showcase-of-beautiful-and-fresh-ecommerce-websites/",
  "publishedDate": 1295941399,
  "tags": [
    {
      "name": "E-Commerce",
      "slug": "e-commerce"
    },
    {
      "name": "Inspiration",
      "slug": "inspiration"
    },
    {
      "name": "Showcases",
      "slug": "showcases"
    },
    {
      "name": "Web Design",
      "slug": "web-design"
    }
  ],
  "title": "Showcase of Beautiful (or Creative) E-Commerce Websites",
  "url": "https://www.smashingmagazine.com/2011/01/showcase-of-beautiful-and-fresh-ecommerce-websites/"
}