{
  "author": "The Smashing Editorial",
  "authorUrl": "https://www.smashingmagazine.com/author/admin/",
  "commentCount": 173,
  "description": "This Balita theme is dedicated to shops that sell products for children. The theme is absolutely free to use for both private and commerical projects.",
  "image": "https://media-mediatemple.netdna-ssl.com/wp-content/uploads/images/post-pictures/balita-theme-illu.jpg",
  "objectID": "https://www.smashingmagazine.com/2011/10/free-e-commerce-wordpress-theme-balita/",
  "publishedDate": 1318984320,
  "tags": [
    {
      "name": "E-Commerce",
      "slug": "e-commerce"
    },
    {
      "name": "Freebies",
      "slug": "freebies"
    },
    {
      "name": "Themes",
      "slug": "themes"
    }
  ],
  "title": "Free E-Commerce WordPress Theme: Balita",
  "url": "https://www.smashingmagazine.com/2011/10/free-e-commerce-wordpress-theme-balita/"
}