{
  "author": "@smashingmag",
  "commentCount": 65,
  "description": "This post features free desktop wallpapers for May 2012. Versions with a calendar and without a calendar are available.",
  "image": "https://media-mediatemple.netdna-ssl.com/wp-content/uploads/images/post-pictures/may2012-illu.jpg",
  "objectID": "https://www.smashingmagazine.com/2012/04/desktop-wallpaper-calendars-may-2012/",
  "publishedDate": 1335787432,
  "tags": [
    "Wallpapers"
  ],
  "title": "Desktop Wallpaper Calendars: May 2012",
  "url": "https://www.smashingmagazine.com/2012/04/desktop-wallpaper-calendars-may-2012/"
}