{
  "author": "Siobhan McKeown",
  "authorUrl": "https://www.smashingmagazine.com/author/siobhan-mckeown/",
  "commentCount": 25,
  "description": "Learn how to write effective documentation for WordPress end-users.",
  "image": "https://media-mediatemple.netdna-ssl.com/wp-content/uploads/images/post-pictures/tools-06.jpg",
  "objectID": "https://www.smashingmagazine.com/2012/07/writing-effective-wordpress-documentation/",
  "publishedDate": 1341357346,
  "tags": [
    {
      "name": "Techniques (WP)",
      "slug": "techniques--wp-"
    }
  ],
  "title": "Writing Effective Documentation For WordPress End Users",
  "url": "https://www.smashingmagazine.com/2012/07/writing-effective-wordpress-documentation/"
}