{
  "author": "@smashingmag",
  "commentCount": 27,
  "description": "Like most well-designed things, the magic of an iPad app comes from a union of usefulness, usability and meaning. Games aside, the app must be useful by solving a problem that people actually have ...",
  "image": "https://media-mediatemple.netdna-ssl.com/wp-content/uploads/images/post-pictures/coversml.jpg",
  "objectID": "https://www.smashingmagazine.com/2012/01/ten-things-to-think-about-when-designing-your-ipad-app/",
  "publishedDate": 1328032612,
  "tags": [
    "Apps",
    "Usability",
    "iPad"
  ],
  "title": "Ten Things To Think About When Designing Your iPad App",
  "url": "https://www.smashingmagazine.com/2012/01/ten-things-to-think-about-when-designing-your-ipad-app/"
}