{
  "author": "The Smashing Editorial",
  "authorUrl": "https://www.smashingmagazine.com/author/admin/",
  "commentCount": 43,
  "description": "Freely available brands icon set featuring icons of popular online brands and the color from their corporate style guides.",
  "image": "https://media-mediatemple.netdna-ssl.com/wp-content/uploads/images/post-pictures/readability.png",
  "objectID": "https://www.smashingmagazine.com/2013/03/free-brand-icons-color-style-guides-icons/",
  "publishedDate": 1362923676,
  "tags": [
    {
      "name": "Freebies",
      "slug": "freebies"
    },
    {
      "name": "Icons",
      "slug": "icons"
    },
    {
      "name": "Style Guides",
      "slug": "style-guides"
    }
  ],
  "title": "Freebie: Brands Icons And Color Style Guides (100 Icons, PNG) | Smashing Magazine",
  "url": "https://www.smashingmagazine.com/2013/03/free-brand-icons-color-style-guides-icons/"
}