{
  "author": "@hvost",
  "commentCount": 30,
  "description": "In this article Artiom Dashinsky shares Slice it and Retinize it, two time-saving Photoshop actions for slicing graphics for Retina and standard displays.",
  "image": "https://media-mediatemple.netdna-ssl.com/wp-content/uploads/2013/07/steps1_mini.jpg",
  "objectID": "https://www.smashingmagazine.com/2013/07/retinize-it-photoshop-action-slicing-graphics-retina/",
  "publishedDate": 1373360413,
  "tags": [
    "Freebies",
    "Photoshop"
  ],
  "title": "Retinize It: Free Photoshop Action For Slicing Graphics For HD Screens",
  "url": "https://www.smashingmagazine.com/2013/07/retinize-it-photoshop-action-slicing-graphics-retina/"
}