{
  "author": "Andy Rutledge",
  "authorUrl": "https://www.smashingmagazine.com/author/andy-rutledge/",
  "commentCount": 20,
  "description": "This article explains how to prepare for a succesful designer-client relationship.",
  "image": "https://media-mediatemple.netdna-ssl.com/wp-content/uploads/images/post-pictures/psych-5.jpg",
  "objectID": "https://www.smashingmagazine.com/2013/01/getting-engaged/",
  "publishedDate": 1357562252,
  "tags": [
    {
      "name": "Business",
      "slug": "business"
    },
    {
      "name": "Clients",
      "slug": "clients"
    },
    {
      "name": "Inspiration",
      "slug": "inspiration"
    }
  ],
  "title": "Getting Engaged",
  "url": "https://www.smashingmagazine.com/2013/01/getting-engaged/"
}