{
  "author": "Paul Boag",
  "authorUrl": "https://www.smashingmagazine.com/author/paul-boag/",
  "commentCount": 13,
  "description": "The business and internal systems of many organizations have shocking user interfaces. This costs companies in productivity, training and even the customer experience.",
  "image": "https://media-mediatemple.netdna-ssl.com/wp-content/uploads/2014/09/different-functionalities-opt.jpg",
  "objectID": "https://www.smashingmagazine.com/2014/09/are-your-internal-systems-damaging-your-business/",
  "publishedDate": 1410526793,
  "tags": [
    {
      "name": "Business",
      "slug": "business"
    },
    {
      "name": "Clients",
      "slug": "clients"
    },
    {
      "name": "Opinion Column",
      "slug": "opinion-column"
    }
  ],
  "title": "Are Your Internal Systems Damaging Your Business?",
  "url": "https://www.smashingmagazine.com/2014/09/are-your-internal-systems-damaging-your-business/"
}