{
  "author": "@twostepmedia",
  "commentCount": 48,
  "description": "Function binding is probably your least concern when beginning with JavaScript, but when you realize that you need a solution to the problem of how to keep the context of this within another functi...",
  "image": "https://media-mediatemple.netdna-ssl.com/wp-content/uploads/2011/04/javascript-292.jpg",
  "objectID": "https://www.smashingmagazine.com/2014/01/understanding-javascript-function-prototype-bind/",
  "publishedDate": 1390438020,
  "tags": [
    "JavaScript",
    "Techniques",
    "Tools"
  ],
  "title": "Understanding JavaScript’s Function.prototype.bind",
  "url": "https://www.smashingmagazine.com/2014/01/understanding-javascript-function-prototype-bind/"
}