{
  "author": "Scott O'Hara",
  "authorUrl": "https://www.smashingmagazine.com/author/scottohara/",
  "commentCount": 46,
  "description": "Modal windows quickly shift focus from one area to another – this can be confusing. Scott O&#39;Hara shows how to make modal windows more usable and accessible.",
  "image": "https://media-mediatemple.netdna-ssl.com/wp-content/uploads/2014/09/illu-modals.jpg",
  "objectID": "https://www.smashingmagazine.com/2014/09/making-modal-windows-better-for-everyone/",
  "publishedDate": 1410776609,
  "tags": [
    {
      "name": "Accessibility",
      "slug": "accessibility"
    },
    {
      "name": "JavaScript",
      "slug": "javascript"
    },
    {
      "name": "Semantics",
      "slug": "semantics"
    },
    {
      "name": "User Experience",
      "slug": "user-experience"
    }
  ],
  "title": "Making Modal Windows Better For Everyone",
  "url": "https://www.smashingmagazine.com/2014/09/making-modal-windows-better-for-everyone/"
}